daxs/__init__.py
daxs/config.py
daxs/correctors.py
daxs/filters.py
daxs/interpolators.py
daxs/measurements.py
daxs/scans.py
daxs/sources.py
daxs/tests/__init__.py
daxs/tests/test_correctors.py
daxs/tests/test_filters.py
daxs/tests/test_import.py
daxs/tests/test_measurements.py
daxs/tests/test_scans.py
daxs/tests/test_sources.py
daxs/utils/__init__.py
daxs/utils/arrays.py
daxs/utils/bragg.py
daxs/utils/material.py
daxs-2026.1.dist-info/licenses/LICENSE
daxs-2026.1.dist-info/METADATA
daxs-2026.1.dist-info/WHEEL
daxs-2026.1.dist-info/top_level.txt
daxs-2026.1.dist-info/RECORD
