Metadata-Version: 2.4
Name: daxs
Version: 2026.1
Summary: Data Analysis for X-ray Spectroscopy
Author-email: Marius Retegan <marius.retegan@esrf.fr>
License-Expression: MIT
Project-URL: Homepage, https://gitlab.esrf.fr/spectroscopy/daxs
Project-URL: Source, https://gitlab.esrf.fr/spectroscopy/daxs
Project-URL: Documentation, https://spectroscopy.gitlab-pages.esrf.fr/daxs
Project-URL: Tracker, https://gitlab.esrf.fr/spectroscopy/daxs/issues
Classifier: Intended Audience :: Science/Research
Classifier: Programming Language :: Python :: 3
Classifier: Programming Language :: Python :: 3 :: Only
Requires-Python: >=3.10
License-File: LICENSE
Requires-Dist: matplotlib
Requires-Dist: numpy
Requires-Dist: scipy
Requires-Dist: silx
Requires-Dist: ruamel.yaml
Requires-Dist: blissdata
Provides-Extra: dev
Requires-Dist: build; extra == "dev"
Requires-Dist: twine; extra == "dev"
Requires-Dist: ruff; extra == "dev"
Requires-Dist: pytest; extra == "dev"
Requires-Dist: pytest-cov; extra == "dev"
Provides-Extra: doc
Requires-Dist: ipympl; extra == "doc"
Requires-Dist: ipykernel; extra == "doc"
Requires-Dist: nbsphinx; extra == "doc"
Requires-Dist: nbsphinx-link; extra == "doc"
Requires-Dist: sphinx~=8.0; extra == "doc"
Requires-Dist: sphinx-copybutton; extra == "doc"
Requires-Dist: pydata-sphinx-theme; extra == "doc"
Dynamic: license-file
